{
  "materials": {
    "material/quad": {
      "name": "Quad Material",
      "material_type": "textured",
      "render_mask": 1,
      "texture_lookups": {
        "base_color": "texture/imagery/tulips"
      }
    },
    "material/multi_bind": {
      "name": "Multi Bind Quad",
      "material_type": "textured",
      "render_mask": 3,
      "texture_lookups": {
        "base_color": "texture/imagery/tulips",
        "emissive": "texture/imagery/peppers"
      }
    },
    "material/bind_table": {
      "name": "Bind Table Quad",
      "material_type": "textured",
      "render_mask": 2,
      "texture_lookups": {
        "base_color": "texture/imagery/peppers"
      }
    }
  }
}
